mpl_fontkit/__init__.py
mpl_fontkit/core.py
mpl_fontkit/download.py
mpl_fontkit-0.5.1.dist-info/WHEEL
mpl_fontkit-0.5.1.dist-info/METADATA
mpl_fontkit-0.5.1.dist-info/RECORD
