Metadata-Version: 2.1
Name: mpl_fontkit
Version: 0.5.1
Summary: Easy font management for Matplotlib.
Author-email: Mr-Milk <zym.zym1220@gmail.com>
Requires-Python: >= 3.8
Classifier: License :: OSI Approved :: MIT License
Classifier: Programming Language :: Python :: 3
Classifier: Framework :: Matplotlib
Classifier: Intended Audience :: Science/Research
Classifier: Intended Audience :: Developers
Classifier: Topic :: Scientific/Engineering :: Visualization
Requires-Dist: matplotlib
Requires-Dist: httpx
Requires-Dist: platformdirs
Requires-Dist: thefuzz
Project-URL: Homepage, https://github.com/Marsilea-viz/mpl_fontkit
